{
	"next_topic_id": 1,
	"topic": [],
	"topic_vote": {},
	"next_comment_id": 5,
	"comment": {
		"2_193GRQHrQgpudYtUXtPkUp7z6DdYWkLfJX": [
			{
				"comment_id": 1,
				"body": "Hola a todos desde España!",
				"added": 1457044999
			},
			{
				"comment_id": 2,
				"body": "> [bitfish](#comment_3_1FfLoFiiFnaf2RPE4nqHEP8mB9uU2rPTmH): Hablo muy poco espanol.\n\ndesde donde escribes?",
				"added": 1457045392
			},
			{
				"comment_id": 3,
				"body": "> [tensai](#comment_1_1MFKUjEuTW7cRkNG4j5PurqTg78oFFaMBr): Buenas! Alguien me podria explicar como buscar sitios en la 0list?\n\nentra aquí http://127.0.0.1:43110/1PLAYgDQboKojowD3kwdb3CtWmWaokXvfp donde podrás encontrar las películas. Casi todo está en inglés",
				"added": 1457045524
			},
			{
				"comment_id": 4,
				"body": "> [francisco](#comment_1_1PNtKfkvkLtSuXPWNrkrbvuq4RXip6QMZ): Tambien quiero saber! Saludos!\n\nentra aquí http://127.0.0.1:43110/1PLAYgDQboKojowD3kwdb3CtWmWaokXvfp donde podrás encontrar las películas. Casi todo está en inglés",
				"added": 1457074217
			}
		]
	},
	"comment_vote": {}
}