{
	"next_topic_id": 2,
	"topic": [
		{
			"topic_id": 1,
			"title": "ZeroRandom - ( Random Shit )",
			"body": "http://127.0.0.1:43110/1BmDLy9bzNM33GuJCtwH1V5LN3KygH2WPh/",
			"added": 1475110848
		}
	],
	"topic_vote": {
		"1_1Psc4YYyrL4T8gnPfQCTyh1b7kTuBuDAEY": 1
	},
	"next_comment_id": 3,
	"comment": {
		"1_1Psc4YYyrL4T8gnPfQCTyh1b7kTuBuDAEY": [
			{
				"comment_id": 1,
				"body": "Fucking UPdate :3",
				"added": 1475123077
			},
			{
				"comment_id": 2,
				"body": "Anybody can help me fix that shit: Site:1BmDLy..2WPh content.json: Site too large 23216230 > 10485760, aborting task...\n??",
				"added": 1475125770
			}
		]
	},
	"comment_vote": {}
}