{
	"next_topic_id": 2,
	"topic": [
		{
			"topic_id": 1,
			"title": "Lsyk4",
			"body": "",
			"added": 1457498179
		}
	],
	"topic_vote": {
		"1_1KERyhfQVoE8GtDRFyWvJVb5KtACzDDh3A": 1
	},
	"next_comment_id": 3,
	"comment": {
		"1_1KERyhfQVoE8GtDRFyWvJVb5KtACzDDh3A": [
			{
				"comment_id": 1,
				"body": "No se si habrá alguien que hable español por acá (tengo a penas unos 10 minutos de estar en ZeroNet). Pero por si lo hay ¡Saludos!",
				"added": 1457498575
			}
		],
		"2_193GRQHrQgpudYtUXtPkUp7z6DdYWkLfJX": [
			{
				"comment_id": 2,
				"body": "¿Y si quieres tener un sitio web en zeronet como haces? (Perdón la ignorancia xD)",
				"added": 1457503971
			}
		]
	},
	"comment_vote": {
		"5_1NzjwWNcVjsX1ndBgkgC1EM5EUzMACGm8L": 1
	}
}