{
	"next_topic_id": 1,
	"topic": [],
	"topic_vote": {},
	"next_comment_id": 3,
	"comment": {
		"2_193GRQHrQgpudYtUXtPkUp7z6DdYWkLfJX": [
			{
				"comment_id": 1,
				"body": "Hola gente!\ndescubriendo todo esto desde Guadalajara (España)\n¿Algun consejo? >Soy novato total",
				"added": 1457288322
			}
		],
		"2_1LPrQCYEyVA3Pz3gEVEf7Qc2z12QGNCSbd": [
			{
				"comment_id": 2,
				"body": "not found",
				"added": 1457290101
			}
		]
	},
	"comment_vote": {
		"1_16hZTsC88EhrnayPacQ9tS8QSkcY7qP2XD": 1
	}
}