{
	"next_topic_id": 2,
	"topic": [
		{
			"topic_id": 1,
			"title": "FairCoin Info",
			"body": "http://127.0.0.1:43110/151fgkx59GMjmbs74PESGrkrAjGDKb5cD3",
			"added": 1456999451
		}
	],
	"topic_vote": {
		"1_1Ad65ppm6jjuP1rzFTQZRGzBHVGWk8EcyA": 1,
		"1_1HSBkju9y9tQrpph3yKgcdzxM6pnkvgmNy": 1
	},
	"next_comment_id": 3,
	"comment": {
		"1_1HSBkju9y9tQrpph3yKgcdzxM6pnkvgmNy": [
			{
				"comment_id": 1,
				"body": "I don't know why it doesn't show the title...",
				"added": 1456999754
			},
			{
				"comment_id": 2,
				"body": "> [kaffie](#comment_5_1NWh3WAty57FH8at1WtrZigMrdhrDkuPzh): Click and drag the top right icon to the left. Scroll down and there'll be a section called \"Site Title\". Set it to what you want and hit 'save changes'. Then sign/publish.\n\nThank you! I dind't even notice there was a menu hidden there :)",
				"added": 1457001603
			}
		]
	},
	"comment_vote": {}
}