{
	"next_topic_id": 4,
	"topic": [
		{
			"topic_id": 1,
			"title": "Lorenzo52",
			"body": "http://127.0.0.1:43110/138iZ6d6UA1ddwh5h8utDtT7TuSBBYi5Jx",
			"added": 1458575989
		},
		{
			"topic_id": 2,
			"title": "nhkkh",
			"body": "",
			"added": 1458576218
		},
		{
			"topic_id": 3,
			"title": "lorenzo52",
			"body": "lorenzo52>127.0.0.1:43110/a3872b39f374e41a78e1f91849de4fa5b3cbdf7d656e6a9cf01352895d3a92b3",
			"added": 1458581120
		}
	],
	"topic_vote": {},
	"next_comment_id": 2,
	"comment": {
		"1_1DKAz1viuEUftnriMGjC7qyZ6bwStoX3y2": [
			{
				"comment_id": 1,
				"body": "hello people",
				"added": 1458576137
			}
		]
	},
	"comment_vote": {}
}